hetmatpy/__init__.py
hetmatpy/degree_group.py
hetmatpy/degree_weight.py
hetmatpy/diffusion.py
hetmatpy/matrix.py
hetmatpy/pipeline.py
hetmatpy/testing.py
hetmatpy/xarray.py
hetmatpy/hetmat/__init__.py
hetmatpy/hetmat/archive.py
hetmatpy/hetmat/caching.py
hetmatpy/hetmat/tests/test_archive.py
hetmatpy/hetmat/tests/test_caching.py
hetmatpy/hetmat/tests/test_hetmat.py
hetmatpy/tests/test_degree_weight.py
hetmatpy/tests/test_diffusion.py
hetmatpy/tests/test_hetnetpy.py
hetmatpy/tests/test_path_count.py
hetmatpy/tests/test_pipeline.py
hetmatpy-0.1.0.dist-info/LICENSE.md
hetmatpy-0.1.0.dist-info/METADATA
hetmatpy-0.1.0.dist-info/WHEEL
hetmatpy-0.1.0.dist-info/top_level.txt
hetmatpy-0.1.0.dist-info/RECORD
