Metadata-Version: 2.1
Name: hetmatpy
Version: 0.1.0
Summary: Matrix implementations for hetnets and path-count-based measures
Home-page: https://het.io/software/
License: # BSD-2-Clause Plus Patent License
Project-URL: Source, https://github.com/hetio/hetmatpy
Project-URL: Documentation, https://hetio.github.io/hetmatpy
Project-URL: Tracker, https://github.com/hetio/hetmatpy/issues
Project-URL: Homepage, https://het.io/software/
Project-URL: Publication, https://greenelab.github.io/connectivity-search-manuscript/
Keywords: hetnet,hetmat,graph,heterogeneous,network,hetio,hetnetpy,dwpc,numpy
Platform: UNKNOWN
Classifier: Intended Audience :: Science/Research
Classifier: Topic :: Scientific/Engineering :: Bio-Informatics
Classifier: Topic :: Scientific/Engineering :: Information Analysis
Requires-Python: >=3.7
License-File: LICENSE.md
Requires-Dist: hetnetpy (>=0.3.0)
Requires-Dist: numpy
Requires-Dist: pandas
Requires-Dist: scipy
Provides-Extra: dev
Requires-Dist: pre-commit ; extra == 'dev'
Requires-Dist: portray ; extra == 'dev'
Requires-Dist: pytest ; extra == 'dev'
Requires-Dist: xarray ; extra == 'dev'
